{"batchcomplete":"","query":{"categorymembers":[{"pageid":946929,"ns":0,"title":"Bionics"},{"pageid":38555995,"ns":0,"title":"Argus retinal prosthesis"},{"pageid":37974009,"ns":0,"title":"Bebionic"},{"pageid":35439884,"ns":0,"title":"Bio-inspired robotics"},{"pageid":31615192,"ns":0,"title":"Biomimetic antifouling coating"},{"pageid":45784,"ns":0,"title":"Biomimetics"},{"pageid":46434772,"ns":0,"title":"BionicKangaroo"},{"pageid":241649,"ns":0,"title":"Cochlear implant"},{"pageid":42334950,"ns":0,"title":"Cybathlon"},{"pageid":39914061,"ns":0,"title":"Direct acoustic cochlear implant"},{"pageid":12681282,"ns":0,"title":"Internalnet"},{"pageid":50569286,"ns":0,"title":"Limbitless Solutions"},{"pageid":6793105,"ns":0,"title":"Mercedes-Benz Bionic"},{"pageid":38454848,"ns":0,"title":"Michelangelo Hand"},{"pageid":49312388,"ns":0,"title":"Open Bionics"},{"pageid":7701587,"ns":0,"title":"Ottobock"},{"pageid":49821898,"ns":0,"title":"Polymer sponge"},{"pageid":489930,"ns":0,"title":"Viktor Schauberger"},{"pageid":52344552,"ns":0,"title":"The Biosphere Rules"}]}}