{"batchcomplete":"","query":{"categorymembers":[{"pageid":9587,"ns":0,"title":"Euthanasia"},{"pageid":166146,"ns":0,"title":"Advance healthcare directive"},{"pageid":631308,"ns":0,"title":"Animal euthanasia"},{"pageid":162615,"ns":0,"title":"Assisted suicide"},{"pageid":20862068,"ns":0,"title":"Bollinger baby"},{"pageid":2492267,"ns":0,"title":"Brian: Portrait of a Dog"},{"pageid":23712707,"ns":0,"title":"Buddhism and euthanasia"},{"pageid":22441717,"ns":0,"title":"Child euthanasia"},{"pageid":2496538,"ns":0,"title":"Consensual homicide"},{"pageid":930376,"ns":0,"title":"Consistent life ethic"},{"pageid":1588656,"ns":0,"title":"Coup de gr\u00e2ce"},{"pageid":8052493,"ns":0,"title":"CrustaStun"},{"pageid":23647796,"ns":0,"title":"Declaration on Euthanasia"},{"pageid":166811,"ns":0,"title":"Do not resuscitate"},{"pageid":3234180,"ns":0,"title":"Drion's pill"},{"pageid":13662713,"ns":0,"title":"Legality of euthanasia"},{"pageid":30285461,"ns":0,"title":"Euthanasia and the slippery slope"},{"pageid":31573452,"ns":0,"title":"Euthanasia Coaster"},{"pageid":20753177,"ns":0,"title":"Euthanasia device"},{"pageid":40190352,"ns":0,"title":"Euthanasia Prevention Coalition"},{"pageid":4162418,"ns":0,"title":"Euthanasia: Opposing Viewpoints (2000)"},{"pageid":2525513,"ns":0,"title":"Final Exit"},{"pageid":7785502,"ns":0,"title":"International Task Force on Euthanasia and Assisted Suicide"},{"pageid":27200647,"ns":0,"title":"Involuntary euthanasia"},{"pageid":53874711,"ns":0,"title":"List of deaths from legal euthanasia and assisted suicide"},{"pageid":15114072,"ns":0,"title":"Love Among the Ruins. A Romance of the Near Future"},{"pageid":25212754,"ns":0,"title":"Nevis Mountain Dew"},{"pageid":10477944,"ns":0,"title":"Non-voluntary euthanasia"},{"pageid":685764,"ns":0,"title":"Palliative sedation"},{"pageid":18103910,"ns":0,"title":"The Peaceful Pill Handbook"},{"pageid":3926931,"ns":0,"title":"Phenytoin/pentobarbital"},{"pageid":23761626,"ns":0,"title":"Religious views on euthanasia"},{"pageid":370782,"ns":0,"title":"Right to die"},{"pageid":45481,"ns":0,"title":"Soylent Green"},{"pageid":24422245,"ns":0,"title":"Stuck In Neutral"},{"pageid":24130492,"ns":0,"title":"Suicide bag"},{"pageid":22309046,"ns":0,"title":"Suicide tourism"},{"pageid":26824878,"ns":0,"title":"Terminal dehydration"},{"pageid":2548579,"ns":0,"title":"Voluntary euthanasia"},{"pageid":2713891,"ns":0,"title":"Whose Life Is It Anyway? (play)"},{"pageid":6834907,"ns":0,"title":"World Federation of Right to Die Societies"}]}}