{"batchcomplete":"","query":{"categorymembers":[{"pageid":149148,"ns":0,"title":"Roger Ailes"},{"pageid":24244308,"ns":0,"title":"Alex Dowsett"},{"pageid":23747730,"ns":0,"title":"Gunther von Hagens"},{"pageid":16996463,"ns":0,"title":"Thomas Henty"},{"pageid":5357585,"ns":0,"title":"Bob Massie (politician)"},{"pageid":315565,"ns":0,"title":"Jason Robertson"},{"pageid":3354525,"ns":0,"title":"Joe Spinell"},{"pageid":42280289,"ns":0,"title":"Christopher Statton"},{"pageid":34415372,"ns":0,"title":"Julian Wintle"}]}}