{"batchcomplete":"","query":{"categorymembers":[{"pageid":72842,"ns":0,"title":"Antofagasta Region"},{"pageid":897099,"ns":0,"title":"Arica"},{"pageid":56602,"ns":0,"title":"Astana"},{"pageid":24250561,"ns":0,"title":"\u2018Aziziya"},{"pageid":4566,"ns":0,"title":"Baku"},{"pageid":2009032,"ns":0,"title":"Cherrapunji"},{"pageid":5618599,"ns":0,"title":"Dallol, Ethiopia"},{"pageid":46797,"ns":0,"title":"Death Valley"},{"pageid":736240,"ns":0,"title":"Extremes on Earth"},{"pageid":53165275,"ns":0,"title":"East Base"},{"pageid":674486,"ns":0,"title":"Eureka, Nunavut"},{"pageid":47551734,"ns":0,"title":"Highest temperature recorded on Earth"},{"pageid":150733,"ns":0,"title":"Holt, Missouri"},{"pageid":57152889,"ns":0,"title":"Index of weather extremes in Australia articles"},{"pageid":325181,"ns":0,"title":"Keelung"},{"pageid":54391326,"ns":0,"title":"List of countries by extreme temperatures"},{"pageid":9862901,"ns":0,"title":"List of extreme temperatures in Canada"},{"pageid":4506267,"ns":0,"title":"List of weather records"},{"pageid":55116359,"ns":0,"title":"List of wettest tropical cyclones"},{"pageid":10329042,"ns":0,"title":"List of wettest tropical cyclones by country"},{"pageid":10531004,"ns":0,"title":"Llor\u00f3"},{"pageid":270811,"ns":0,"title":"Lowest temperature recorded on Earth"},{"pageid":48823,"ns":0,"title":"Malabo"},{"pageid":804123,"ns":0,"title":"Marble Bar, Western Australia"},{"pageid":1131393,"ns":0,"title":"Mawsynram"},{"pageid":566327,"ns":0,"title":"Oymyakon"},{"pageid":28467978,"ns":0,"title":"List of extreme weather records in Pakistan"},{"pageid":1464304,"ns":0,"title":"Pole of Cold"},{"pageid":945689,"ns":0,"title":"Quibd\u00f3"},{"pageid":14248647,"ns":0,"title":"Quillagua"},{"pageid":29461662,"ns":0,"title":"San Antonio de Ureca"},{"pageid":134923,"ns":0,"title":"Spearfish, South Dakota"},{"pageid":43979,"ns":0,"title":"T\u00f3rshavn"},{"pageid":57915,"ns":0,"title":"Verkhoyansk"},{"pageid":424335,"ns":0,"title":"Vostok Station"},{"pageid":1380151,"ns":0,"title":"Mount Waialeale"},{"pageid":165198,"ns":0,"title":"Wind speed"},{"pageid":106806,"ns":0,"title":"Yuma, Arizona"}]}}