{"batchcomplete":"","query":{"categorymembers":[{"pageid":39641385,"ns":14,"title":"Category:Lists of cardinals by papal appointment"},{"pageid":25271808,"ns":14,"title":"Category:Cardinals created by Pope Benedict XVI"},{"pageid":41620608,"ns":14,"title":"Category:Cardinals created by Pope Francis"},{"pageid":51861854,"ns":14,"title":"Category:Cardinals created by Pope Gregory XIII"},{"pageid":40024434,"ns":14,"title":"Category:Cardinals created by Pope Innocent XI"},{"pageid":25503584,"ns":14,"title":"Category:Cardinals created by Pope John XXIII"},{"pageid":25271772,"ns":14,"title":"Category:Cardinals created by Pope John Paul II"},{"pageid":25272244,"ns":14,"title":"Category:Cardinals created by Pope Paul VI"},{"pageid":31908325,"ns":14,"title":"Category:Cardinals created by Pope Pius VI"},{"pageid":25243936,"ns":14,"title":"Category:Cardinals created by Pope Pius XI"},{"pageid":16663752,"ns":14,"title":"Category:Cardinals created by Pope Pius XII"}]}}